chip_cud_prompt/__init__.py
chip_cud_prompt/abstract_prompt_manager.py
chip_cud_prompt/chip_create_prompt.py
chip_cud_prompt-0.0.3.dist-info/LICENSE
chip_cud_prompt-0.0.3.dist-info/METADATA
chip_cud_prompt-0.0.3.dist-info/WHEEL
chip_cud_prompt-0.0.3.dist-info/top_level.txt
chip_cud_prompt-0.0.3.dist-info/RECORD
