Metadata-Version: 2.1
Name: chip_cud_prompt
Version: 0.0.3
Summary: A prompt package
Author-email: zkhCreator <zkh90644@gmail.com>
Project-URL: Homepage, https://github.com/zkhCreator/chip-cud-prompt
Project-URL: Issues, https://github.com/zkhCreator/chip-cud-prompt/issues
Classifier: Programming Language :: Python :: 3
Classifier: License :: OSI Approved :: MIT License
Classifier: Operating System :: OS Independent
Requires-Python: >=3.10
License-File: LICENSE
